Topsis_Punya_102303567/__init__.py
Topsis_Punya_102303567/topsis.py
topsis_punya_102303567-1.0.0.dist-info/licenses/LICENSE
topsis_punya_102303567-1.0.0.dist-info/METADATA
topsis_punya_102303567-1.0.0.dist-info/WHEEL
topsis_punya_102303567-1.0.0.dist-info/entry_points.txt
topsis_punya_102303567-1.0.0.dist-info/top_level.txt
topsis_punya_102303567-1.0.0.dist-info/RECORD
