Metadata-Version: 2.4
Name: Topsis-Punya-102303567
Version: 1.0.0
Summary: A Python package to implement TOPSIS
Home-page: https://github.com/punyey/assignment1_DS
Author: Punya
Author-email: punya@example.com
Classifier: Programming Language :: Python :: 3
Classifier: License :: OSI Approved :: MIT License
Classifier: Operating System :: OS Independent
License-File: LICENSE
Dynamic: author
Dynamic: author-email
Dynamic: classifier
Dynamic: description
Dynamic: description-content-type
Dynamic: home-page
Dynamic: license-file
Dynamic: summary
